cake/__init__.py
cake/abc.py
cake/digits.py
cake/errors.py
cake/helpers.py
cake/sympy.py
cake/core/__init__.py
cake/core/markers.py
cake/core/surd.py
cake/core/unknown.py
cake/core/number/__init__.py
cake/core/number/number.py
cake/core/number/ops.py
cake/core/types/__init__.py
cake/core/types/complex.py
cake/core/types/float.py
cake/core/types/integer.py
cake/core/types/irrational.py
cake/core/types/prime.py
cake/formatters/__init__.py
cake/fractions/__init__.py
cake/fractions/fractions.py
cake/functions/__init__.py
cake/functions/base.py
cake/functions/prime.py
cake/functions/basic/__init__.py
cake/functions/basic/trig.py
cake/graphs/__init__.py
cake/graphs/graphlogic.py
cake/matrices/__init__.py
cake/matrices/matrix.py
cake/matrices/shorthand.py
cake/parsing/__init__.py
cake/parsing/equation.py
cake/parsing/expression.py
MathCake-0.0.1a3.dist-info/LICENSE
MathCake-0.0.1a3.dist-info/METADATA
MathCake-0.0.1a3.dist-info/WHEEL
MathCake-0.0.1a3.dist-info/top_level.txt
MathCake-0.0.1a3.dist-info/RECORD
