Metadata-Version: 2.1
Name: MathCake
Version: 0.0.1a3
Summary: An object orientated math library
Home-page: https://github.com/Mecha-Karen/Cake
Author: Mecha Karen
License: MIT License
Project-URL: Documentation, https://docs.mechakaren.xyz/cake
Project-URL: Issue tracker, https://github.com/Mecha-Karen/Cake/issues
Project-URL: Organisation, https://github.com/Mecha-Karen
Keywords: Math,Python3,OOP
Platform: UNKNOWN
Classifier: Development Status :: 1 - Planning
Classifier: Intended Audience :: Developers
Classifier: Operating System :: OS Independent
Classifier: License :: OSI Approved :: MIT License
Classifier: Programming Language :: Python :: 3
License-File: LICENSE
